awklite/__init__.py
nemo/__init__.py
nemo/configfile.py
nemo/context.py
nemo/costs.py
nemo/demand.py
nemo/generators.py
nemo/nem.py
nemo/penalties.py
nemo/polygons.py
nemo/regions.py
nemo/scenarios.py
nemo/sim.py
nemo/types.py
nemo/utils.py
nemopt-20230323.data/data/etc/nemo.cfg
nemopt-20230323.data/scripts/evolve
nemopt-20230323.data/scripts/replay
nemopt-20230323.data/scripts/summary
nemopt-20230323.dist-info/COPYING
nemopt-20230323.dist-info/METADATA
nemopt-20230323.dist-info/WHEEL
nemopt-20230323.dist-info/top_level.txt
nemopt-20230323.dist-info/RECORD
