Metadata-Version: 2.1
Name: nemopt
Version: 20230323
Summary: National Electricity Market Optimiser
Home-page: https://nemo.ozlabs.org
Author: Ben Elliston
Author-email: bje@air.net.au
License: GPLv3
Keywords: electricity,model,scenarios
Classifier: Development Status :: 5 - Production/Stable
Classifier: Environment :: Console
Classifier: Environment :: X11 Applications
Classifier: Intended Audience :: Science/Research
Classifier: License :: OSI Approved :: GNU General Public License v3 (GPLv3)
Classifier: Programming Language :: Python :: 3 :: Only
Classifier: Topic :: Scientific/Engineering
License-File: COPYING
Requires-Dist: deap
Requires-Dist: Gooey (>=1.0.4)
Requires-Dist: matplotlib
Requires-Dist: numpy
Requires-Dist: pandas
Requires-Dist: pint
Requires-Dist: requests
